{
  "elements": [
    {
      "element": {
        "element_type": "valhelsia_structures:valhelsia_single",
        "location": "valhelsia_structures:spawner_dungeon/entrance/entrance_1",
        "processors": "valhelsia_structures:remove_water",
        "projection": "rigid"
      },
      "weight": 1
    },
    {
      "element": {
        "element_type": "valhelsia_structures:valhelsia_single",
        "location": "valhelsia_structures:spawner_dungeon/entrance/entrance_2",
        "processors": "valhelsia_structures:remove_water",
        "projection": "rigid"
      },
      "weight": 1
    }
  ],
  "fallback": "minecraft:empty"
}